{
  "version": "1.0",
  "generated_at": "2026-04-11T15:32:36.101524-03:00",
  "generated_by": "GLM-4.7",
  "expires_at": "2026-04-12T15:32:36.101524-03:00",
  "last_analyzed_commit": "15dbb6af329487b19aba7c16f29acfebbc14a6e0",
  "summary": "A modular Go CLI tool for controlling and querying various macOS system components and settings.",
  "architecture": "modular monolith",
  "primary_language": "Go",
  "hot_files": [
    "supermac-go/cmd/mac/main.go",
    "supermac-go/internal/modules/apps/apps.go",
    "supermac-go/internal/modules/dev/dev.go",
    "supermac-go/internal/modules/system/system.go",
    "supermac-go/internal/config/config.go"
  ],
  "patterns": [
    "module pattern",
    "command pattern",
    "internal package encapsulation",
    "standard Go project layout"
  ],
  "concerns": [
    "documentation commits dominating recent activity instead of feature development",
    "uncommitted staged and untracked files indicating incomplete work",
    "missing key files like cmd/mac entrypoint in the provided structure",
    "potential overlap between module/ and modules/ directories"
  ],
  "suggestions": [
    "commit or stash the pending changes to maintain a clean working tree",
    "consolidate module/ and modules/ directories if they serve similar purposes",
    "shift focus from documentation planning to implementing the planned auto-update feature",
    "add unit tests for the core modules (power, network, wifi, dock)"
  ]
}